csotools_serverquery/__init__.py
csotools_serverquery/a2a_ping.py
csotools_serverquery/a2s_info.py
csotools_serverquery/a2s_players.py
csotools_serverquery/a2s_rules.py
csotools_serverquery/common/__init__.py
csotools_serverquery/common/byteio.py
csotools_serverquery/common/constant.py
csotools_serverquery/common/datacls.py
csotools_serverquery/common/exception.py
csotools_serverquery/common/fragment.py
csotools_serverquery/connection/__init__.py
csotools_serverquery/connection/asynchro.py
csotools_serverquery/connection/common.py
csotools_serverquery/connection/constant.py
csotools_serverquery/connection/protocol.py
csotools_serverquery/connection/synchro.py
csotools_serverquery-0.6.0.dist-info/LICENSE
csotools_serverquery-0.6.0.dist-info/WHEEL
csotools_serverquery-0.6.0.dist-info/METADATA
csotools_serverquery-0.6.0.dist-info/RECORD
